ultr_toolbox/__init__.py
ultr_toolbox/click_models/__init__.py
ultr_toolbox/click_models/data.py
ultr_toolbox/click_models/em/__init__.py
ultr_toolbox/click_models/em/trainer.py
ultr_toolbox/click_models/metrics.py
ultr_toolbox/click_models/neural/__init__.py
ultr_toolbox/click_models/neural/base.py
ultr_toolbox/click_models/neural/cm.py
ultr_toolbox/click_models/neural/dbn.py
ultr_toolbox/click_models/neural/loss.py
ultr_toolbox/click_models/neural/pbm.py
ultr_toolbox/click_models/neural/trainer.py
ultr_toolbox/click_models/neural/ubm.py
ultr_toolbox/click_models/stats/__init__.py
ultr_toolbox/click_models/stats/models.py
ultr_toolbox/click_models/stats/trainer.py
ultr_toolbox-0.1.2.dist-info/METADATA
ultr_toolbox-0.1.2.dist-info/WHEEL
ultr_toolbox-0.1.2.dist-info/RECORD
