Metadata-Version: 2.1
Name: ultr-toolbox
Version: 0.1.2
Summary: 
Author: Philipp Hager
Author-email: philipp.konstantin.hager@gmail.com
Requires-Python: >=3.8,<4.0
Classifier: Programming Language :: Python :: 3
Classifier: Programming Language :: Python :: 3.8
Classifier: Programming Language :: Python :: 3.9
Classifier: Programming Language :: Python :: 3.10
Classifier: Programming Language :: Python :: 3.11
Requires-Dist: flax (>=0.7.1,<0.8.0)
Requires-Dist: jax (>=0.4.1,<0.5.0)
Requires-Dist: optax (>=0.1.7,<0.2.0)
Requires-Dist: pandas (>=2.0.3,<3.0.0)
Requires-Dist: pyarrow (>=12.0.1,<13.0.0)
Requires-Dist: torch (>=2.0.1,<3.0.0)
Requires-Dist: tqdm (>=4.65.0,<5.0.0)
